<?xml version="1.0" encoding="utf-8"?>
<!DOCTYPE hibernate-mapping PUBLIC "-//Hibernate/Hibernate Mapping DTD 3.0//EN"
"http://hibernate.sourceforge.net/hibernate-mapping-3.0.dtd">
<!-- 
    Mapping file autogenerated by MyEclipse Persistence Tools
-->
<hibernate-mapping>
    <class name="com.slxt.rs.model.JlFrTemp" table="JL_FR_TEMP">
        <id name="ryid" type="java.lang.Long">
            <column name="ryid" />
        </id>
        <property name="bm" type="java.lang.String">
            <column name="bm" length="50" />
        </property>
        <property name="xm" type="java.lang.String">
            <column name="xm" length="50" />
        </property>
        <property name="xb" type="java.lang.String">
            <column name="xb" length="50" />
        </property>
        <property name="mz" type="java.lang.String">
            <column name="mz" length="50" />
        </property>
        <property name="csrq" type="java.lang.String">
            <column name="csrq" length="50" />
        </property>
        <property name="dw" type="java.lang.String">
            <column name="dw" length="50" />
        </property>
        <property name="zzm" type="java.lang.String">
            <column name="zzm" length="200" />
        </property>
        <property name="jg" type="java.lang.String">
            <column name="jg" length="200" />
        </property>
        <property name="jtzzcs" type="java.lang.String">
            <column name="jtzzcs" length="500" />
        </property>
        <property name="jtzz" type="java.lang.String">
            <column name="jtzz" length="500" />
        </property>
        <property name="rjrq" type="java.lang.String">
            <column name="rjrq" length="50" />
        </property>
        <property name="syrq" type="java.lang.String">
            <column name="syrq" length="50" />
        </property>
        <property name="pjxq" type="java.lang.String">
            <column name="pjxq" length="50" />
        </property>
        <property name="pjqr" type="java.lang.String">
            <column name="pjqr" length="50" />
        </property>
        <property name="pjzr" type="java.lang.String">
            <column name="pjzr" length="50" />
        </property>
        <property name="zxxq" type="java.lang.String">
            <column name="zxxq" length="50" />
        </property>
        <property name="zxxqqr" type="java.lang.String">
            <column name="zxxqqr" length="50" />
        </property>
        <property name="zxxqzr" type="java.lang.String">
            <column name="zxxqzr" length="50" />
        </property>
        <property name="jb" type="java.lang.String">
            <column name="JB" length="50" />
        </property>
         <property name="dah" type="java.lang.String">
            <column name="dah" length="50" />
        </property>
    </class>
</hibernate-mapping>
